README.md
setup.py
alibabacloud_pts20190810/__init__.py
alibabacloud_pts20190810/client.py
alibabacloud_pts20190810/models.py
alibabacloud_pts20190810.egg-info/PKG-INFO
alibabacloud_pts20190810.egg-info/SOURCES.txt
alibabacloud_pts20190810.egg-info/dependency_links.txt
alibabacloud_pts20190810.egg-info/requires.txt
alibabacloud_pts20190810.egg-info/top_level.txt